Metadata-Version: 1.0
Name: byna-dist
Version: 0.1
Summary: Gaussian distributions
Home-page: UNKNOWN
Author: Abubakar Abdusalam
Author-email: abdusalam@bynalab.com
License: UNKNOWN
Platform: UNKNOWN
